{
  "alpha_rows": [
    {
      "alpha": 0.0,
      "Hit@5": 0.471,
      "MRR": 0.355,
      "Recall@5": 0.266
    },
    {
      "alpha": 0.2,
      "Hit@5": 0.588,
      "MRR": 0.418,
      "Recall@5": 0.385
    },
    {
      "alpha": 0.4,
      "Hit@5": 0.618,
      "MRR": 0.493,
      "Recall@5": 0.426
    },
    {
      "alpha": 0.5,
      "Hit@5": 0.647,
      "MRR": 0.515,
      "Recall@5": 0.463
    },
    {
      "alpha": 0.6,
      "Hit@5": 0.824,
      "MRR": 0.586,
      "Recall@5": 0.712
    },
    {
      "alpha": 0.7,
      "Hit@5": 0.912,
      "MRR": 0.691,
      "Recall@5": 0.867
    },
    {
      "alpha": 0.8,
      "Hit@5": 0.912,
      "MRR": 0.706,
      "Recall@5": 0.867
    },
    {
      "alpha": 0.9,
      "Hit@5": 0.912,
      "MRR": 0.721,
      "Recall@5": 0.867
    },
    {
      "alpha": 1.0,
      "Hit@5": 0.941,
      "MRR": 0.768,
      "Recall@5": 0.911
    }
  ],
  "hybrid_alpha": 1.0
}